{
  "$schema": "https://ui.shadcn.com/schema/registry-item.json",
  "name": "field-demo",
  "registryDependencies": [
    "https://herocn.dev/r/button.json",
    "https://herocn.dev/r/checkbox.json",
    "https://herocn.dev/r/field.json",
    "https://herocn.dev/r/input.json",
    "https://herocn.dev/r/select.json",
    "https://herocn.dev/r/textarea.json"
  ],
  "files": [
    {
      "path": "components/examples/field-demo.tsx",
      "content": "\"use client\";\n\nimport { Button } from \"@/components/ui/button\";\nimport { Checkbox } from \"@/components/ui/checkbox\";\nimport {\n  Field,\n  FieldDescription,\n  FieldGroup,\n  FieldLabel,\n  FieldLegend,\n  FieldSeparator,\n  FieldSet,\n} from \"@/components/ui/field\";\nimport { Input } from \"@/components/ui/input\";\nimport {\n  Select,\n  SelectContent,\n  SelectGroup,\n  SelectItem,\n  SelectTrigger,\n  SelectValue,\n} from \"@/components/ui/select\";\nimport { Textarea } from \"@/components/ui/textarea\";\n\nconst months = [\n  { label: \"MM\", value: null },\n  { label: \"01\", value: \"01\" },\n  { label: \"02\", value: \"02\" },\n  { label: \"03\", value: \"03\" },\n  { label: \"04\", value: \"04\" },\n  { label: \"05\", value: \"05\" },\n  { label: \"06\", value: \"06\" },\n  { label: \"07\", value: \"07\" },\n  { label: \"08\", value: \"08\" },\n  { label: \"09\", value: \"09\" },\n  { label: \"10\", value: \"10\" },\n  { label: \"11\", value: \"11\" },\n  { label: \"12\", value: \"12\" },\n];\n\nconst years = [\n  { label: \"YYYY\", value: null },\n  { label: \"2024\", value: \"2024\" },\n  { label: \"2025\", value: \"2025\" },\n  { label: \"2026\", value: \"2026\" },\n  { label: \"2027\", value: \"2027\" },\n  { label: \"2028\", value: \"2028\" },\n  { label: \"2029\", value: \"2029\" },\n];\n\nexport default function FieldDemo() {\n  return (\n    <div className=\"w-full max-w-md\">\n      <form>\n        <FieldGroup>\n          <FieldSet>\n            <FieldLegend>Payment Method</FieldLegend>\n            <FieldDescription>\n              All transactions are secure and encrypted\n            </FieldDescription>\n            <FieldGroup>\n              <Field>\n                <FieldLabel htmlFor=\"checkout-card-name\">\n                  Name on Card\n                </FieldLabel>\n                <Input\n                  id=\"checkout-card-name\"\n                  placeholder=\"Evil Rabbit\"\n                  required\n                />\n              </Field>\n              <Field>\n                <FieldLabel htmlFor=\"checkout-card-number\">\n                  Card Number\n                </FieldLabel>\n                <Input\n                  id=\"checkout-card-number\"\n                  placeholder=\"1234 5678 9012 3456\"\n                  required\n                />\n                <FieldDescription>\n                  Enter your 16-digit card number\n                </FieldDescription>\n              </Field>\n              <div className=\"grid grid-cols-3 gap-4\">\n                <Field>\n                  <FieldLabel htmlFor=\"checkout-exp-month\">Month</FieldLabel>\n                  <Select items={months}>\n                    <SelectTrigger id=\"checkout-exp-month\">\n                      <SelectValue />\n                    </SelectTrigger>\n                    <SelectContent>\n                      <SelectGroup>\n                        {months.map((item, index) => (\n                          <SelectItem\n                            key={`${item.value}-${index}`}\n                            value={item.value}\n                          >\n                            {item.label}\n                          </SelectItem>\n                        ))}\n                      </SelectGroup>\n                    </SelectContent>\n                  </Select>\n                </Field>\n                <Field>\n                  <FieldLabel htmlFor=\"checkout-exp-year\">Year</FieldLabel>\n                  <Select items={years}>\n                    <SelectTrigger id=\"checkout-exp-year\">\n                      <SelectValue />\n                    </SelectTrigger>\n                    <SelectContent>\n                      <SelectGroup>\n                        {years.map((item, index) => (\n                          <SelectItem\n                            key={`${item.value}-${index}`}\n                            value={item.value}\n                          >\n                            {item.label}\n                          </SelectItem>\n                        ))}\n                      </SelectGroup>\n                    </SelectContent>\n                  </Select>\n                </Field>\n                <Field>\n                  <FieldLabel htmlFor=\"checkout-cvv\">CVV</FieldLabel>\n                  <Input id=\"checkout-cvv\" placeholder=\"123\" required />\n                </Field>\n              </div>\n            </FieldGroup>\n          </FieldSet>\n          <FieldSeparator />\n          <FieldSet>\n            <FieldLegend>Billing Address</FieldLegend>\n            <FieldDescription>\n              The billing address associated with your payment method\n            </FieldDescription>\n            <FieldGroup>\n              <Field orientation=\"horizontal\">\n                <Checkbox id=\"same-as-shipping\" defaultChecked />\n                <FieldLabel htmlFor=\"same-as-shipping\" className=\"font-normal\">\n                  Same as shipping address\n                </FieldLabel>\n              </Field>\n            </FieldGroup>\n          </FieldSet>\n          <FieldSet>\n            <FieldGroup>\n              <Field>\n                <FieldLabel htmlFor=\"checkout-comments\">Comments</FieldLabel>\n                <Textarea\n                  id=\"checkout-comments\"\n                  placeholder=\"Add any additional comments\"\n                  className=\"resize-none\"\n                />\n              </Field>\n            </FieldGroup>\n          </FieldSet>\n          <Field orientation=\"horizontal\">\n            <Button type=\"submit\">Submit</Button>\n            <Button variant=\"outline\" type=\"button\">\n              Cancel\n            </Button>\n          </Field>\n        </FieldGroup>\n      </form>\n    </div>\n  );\n}\n",
      "type": "registry:example"
    }
  ],
  "type": "registry:example"
}